{"meta":{"status":"OK","code":"200"},"data":[
  {"id":1,"name":"Header-display-point-1","regions":[
    {"id": 2, "name": "Navigation-region-4", "sequence": "1", "type": "NAVIGATION"}
  ]},
  {"id":2,"name":"Body-display-point-2","regions":[
    {"id": 5, "name": "Report-region-2", "sequence": "2", "type": "REPORT"},
    {"id": 6, "name": "Html-region-1", "sequence": "1", "type": "HTML"},
    {"id": 7, "name": "Form-region-3", "sequence": "3", "type": "FORM"}
  ]},
  {"id":3,"name":"Footer-display-point-3","regions":[]}
]}